setup.py
shinodistributions/Binomialdistribution.py
shinodistributions/Gaussiandistribution.py
shinodistributions/Generaldistribution.py
shinodistributions/__init__.py
shinodistributions.egg-info/PKG-INFO
shinodistributions.egg-info/SOURCES.txt
shinodistributions.egg-info/dependency_links.txt
shinodistributions.egg-info/not-zip-safe
shinodistributions.egg-info/top_level.txt